lazy_loader/__init__.py
lazy_loader/tests/__init__.py
lazy_loader/tests/test_lazy_loader.py
lazy_loader/tests/fake_pkg/__init__.py
lazy_loader/tests/fake_pkg/__init__.pyi
lazy_loader/tests/fake_pkg/some_func.py
lazy_loader-0.3rc0.dist-info/LICENSE.md
lazy_loader-0.3rc0.dist-info/WHEEL
lazy_loader-0.3rc0.dist-info/METADATA
lazy_loader-0.3rc0.dist-info/RECORD
