Metadata-Version: 2.1
Name: lazy_loader
Version: 0.3rc0
Summary: lazy_loader
Author: Scientific Python Developers
Requires-Python: >=3.7
Classifier: Development Status :: 4 - Beta
Classifier: License :: OSI Approved :: BSD License
Classifier: Programming Language :: Python :: 3
Classifier: Programming Language :: Python :: 3.7
Classifier: Programming Language :: Python :: 3.8
Classifier: Programming Language :: Python :: 3.9
Classifier: Programming Language :: Python :: 3.10
Classifier: Programming Language :: Python :: 3.11
Classifier: Programming Language :: Python :: 3.12
Requires-Dist: pre-commit >= 3.3 ; extra == "lint"
Requires-Dist: pytest >= 7.4 ; extra == "test"
Requires-Dist: pytest-cov >= 4.1 ; extra == "test"
Project-URL: Home, https://scientific-python.org/specs/spec-0001/
Project-URL: Source, https://github.com/scientific-python/lazy_loader
Provides-Extra: lint
Provides-Extra: test
